sator_core/__init__.py
sator_core/models/__init__.py
sator_core/models/bug.py
sator_core/models/enums.py
sator_core/models/oss/__init__.py
sator_core/models/oss/diff.py
sator_core/models/patch/__init__.py
sator_core/models/patch/attributes.py
sator_core/models/patch/descriptor.py
sator_core/models/patch/locator.py
sator_core/models/patch/references.py
sator_core/models/product/__init__.py
sator_core/models/product/attributes.py
sator_core/models/product/configuration.py
sator_core/models/product/descriptor.py
sator_core/models/product/locator.py
sator_core/models/product/metadata.py
sator_core/models/product/product.py
sator_core/models/product/references.py
sator_core/models/vulnerability/__init__.py
sator_core/models/vulnerability/attributes.py
sator_core/models/vulnerability/description.py
sator_core/models/vulnerability/descriptor.py
sator_core/models/vulnerability/locator.py
sator_core/models/vulnerability/metadata.py
sator_core/models/vulnerability/references.py
sator_core/ports/__init__.py
sator_core/ports/driven/__init__.py
sator_core/ports/driven/analyzers/__init__.py
sator_core/ports/driven/analyzers/patch.py
sator_core/ports/driven/classifiers/__init__.py
sator_core/ports/driven/classifiers/diff.py
sator_core/ports/driven/classifiers/impact.py
sator_core/ports/driven/classifiers/patch_action.py
sator_core/ports/driven/classifiers/product.py
sator_core/ports/driven/classifiers/weakness.py
sator_core/ports/driven/extraction/__init__.py
sator_core/ports/driven/extraction/attributes/__init__.py
sator_core/ports/driven/extraction/attributes/patch.py
sator_core/ports/driven/extraction/attributes/product.py
sator_core/ports/driven/extraction/attributes/vulnerability.py
sator_core/ports/driven/gateways/__init__.py
sator_core/ports/driven/gateways/oss.py
sator_core/ports/driven/persistence/__init__.py
sator_core/ports/driven/persistence/storage.py
sator_core/ports/driven/repositories/__init__.py
sator_core/ports/driven/repositories/oss.py
sator_core-0.0.17.dist-info/licenses/LICENSE
sator_core-0.0.17.dist-info/METADATA
sator_core-0.0.17.dist-info/WHEEL
sator_core-0.0.17.dist-info/top_level.txt
sator_core-0.0.17.dist-info/RECORD
