Metadata-Version: 2.4
Name: sator-core
Version: 0.0.17
Summary: Package with the core domain logic for Sator, an open-source vulnerability analysis application.
Author-email: Eduard Pinconschi <eduard.pinconschi@tecnico.ulisboa.pt>
Project-URL: repository, https://github.com/epicosy/sator-core
Project-URL: homepage, https://github.com/epicosy/sator-core
Keywords: package,sator,core,hexagonal,architecture
Classifier: Topic :: Software Development
Classifier: Programming Language :: Python
Classifier: Environment :: Console
Classifier: Intended Audience :: Developers
Requires-Python: >=3.10
License-File: LICENSE
Requires-Dist: pydantic>=2.10.3
Provides-Extra: test
Requires-Dist: pytest; extra == "test"
Requires-Dist: pytest-cov; extra == "test"
Requires-Dist: coverage; extra == "test"
Requires-Dist: twine>=1.11.0; extra == "test"
Requires-Dist: setuptools>=38.6.0; extra == "test"
Requires-Dist: wheel>=0.31.0; extra == "test"
Dynamic: license-file
